emflow/__init__.py
emflow/api/__init__.py
emflow/api/auth.py
emflow/api/project.py
emflow/db/__init__.py
emflow/db/localModels.py
emflow/db/models.py
emflow/dist/favicon.ico
emflow/dist/index.html
emflow/dist/manifest.json
emflow/dist/precache-manifest.a89adb7f9f813db051568eed1629bca8.js
emflow/dist/robots.txt
emflow/dist/service-worker.js
emflow/dist/css/app.1b97f328.css
emflow/dist/css/chunk-vendors.cc7c3951.css
emflow/dist/fonts/element-icons.535877f5.woff
emflow/dist/fonts/element-icons.732389de.ttf
emflow/dist/fonts/fontawesome-webfont.674f50d2.eot
emflow/dist/fonts/fontawesome-webfont.af7ae505.woff2
emflow/dist/fonts/fontawesome-webfont.b06871f2.ttf
emflow/dist/fonts/fontawesome-webfont.fee66e71.woff
emflow/dist/img/fontawesome-webfont.912ec66d.svg
emflow/dist/img/icons/android-chrome-192x192.png
emflow/dist/img/icons/android-chrome-512x512.png
emflow/dist/img/icons/apple-touch-icon-120x120.png
emflow/dist/img/icons/apple-touch-icon-152x152.png
emflow/dist/img/icons/apple-touch-icon-180x180.png
emflow/dist/img/icons/apple-touch-icon-60x60.png
emflow/dist/img/icons/apple-touch-icon-76x76.png
emflow/dist/img/icons/apple-touch-icon.png
emflow/dist/img/icons/favicon-16x16.png
emflow/dist/img/icons/favicon-32x32.png
emflow/dist/img/icons/msapplication-icon-144x144.png
emflow/dist/img/icons/mstile-150x150.png
emflow/dist/img/icons/safari-pinned-tab.svg
emflow/dist/js/app.b0ddf162.js
emflow/dist/js/app.b0ddf162.js.map
emflow/dist/js/chunk-vendors.730f5436.js
emflow/dist/js/chunk-vendors.730f5436.js.map
emflow/scripts/auth/run_su.sh
emflow/scripts/conf/cmds.json
emflow/scripts/png/aln2png.py
emflow/scripts/png/extract.py
emflow/scripts/png/mrc2png.py
emflow/services/__init__.py
emflow/services/extract.py
emflow/services/taskServer.py
emflow/tasks/__init__.py
emflow/tasks/shell.py
emflow-0.0.4.dist-info/METADATA
emflow-0.0.4.dist-info/WHEEL
emflow-0.0.4.dist-info/top_level.txt
emflow-0.0.4.dist-info/RECORD
