Metadata-Version: 2.1
Name: emflow
Version: 0.0.4
Summary: UNKNOWN
Home-page: UNKNOWN
Author: DidaZxc
Author-email: didazxc@gmail.com
License: UNKNOWN
Platform: UNKNOWN
Requires-Dist: Flask
Requires-Dist: flask-sqlalchemy
Requires-Dist: dataclasses
Requires-Dist: flask-httpauth
Requires-Dist: flask-cors
Requires-Dist: subprocess.run
Requires-Dist: celery
Requires-Dist: redis (==3.3.11)
Requires-Dist: mrcfile
Requires-Dist: pillow
Requires-Dist: numpy
Requires-Dist: scipy
Requires-Dist: pyfunctional
